LoggerLocalPythonPackage/LoggerService.py
LoggerLocalPythonPackage/LoggerServiceSingleton.py
LoggerLocalPythonPackage/MessageSeverity.py
LoggerLocalPythonPackage/Writer.py
LoggerLocalPythonPackage/__init__.py
logger_local_python_package-0.0.4.dist-info/LICENSE
logger_local_python_package-0.0.4.dist-info/METADATA
logger_local_python_package-0.0.4.dist-info/WHEEL
logger_local_python_package-0.0.4.dist-info/top_level.txt
logger_local_python_package-0.0.4.dist-info/RECORD
