Metadata-Version: 2.1
Name: logger-local-python-package
Version: 0.0.4
Summary: PyPI Package for Circles Logger Python Local
Home-page: https://github.com/circles-zone/logger-local-python-package
Author: Circles
Author-email: info@circles.life
Classifier: Programming Language :: Python :: 3
Classifier: License :: Other/Proprietary License
Classifier: Operating System :: OS Independent
License-File: LICENSE
